road_collisions/__init__.py
road_collisions/constants.py
road_collisions/logging.py
road_collisions/utils.py
road_collisions/bin/__init__.py
road_collisions/bin/load.py
road_collisions/bin/raw_cleaner.py
road_collisions/models/__init__.py
road_collisions/models/collision.py
road_collisions/models/generic.py
road_collisions/models/raw_collision.py
road_collisions/resources/ireland.json
road_collisions-0.0.6.dist-info/METADATA
road_collisions-0.0.6.dist-info/WHEEL
road_collisions-0.0.6.dist-info/entry_points.txt
road_collisions-0.0.6.dist-info/top_level.txt
road_collisions-0.0.6.dist-info/RECORD
