Metadata-Version: 2.1
Name: road_collisions
Version: 0.0.6
Summary: Road collision data and tooling
Home-page: https://github.com/RobertLucey/road-collisions
Author: Robert Lucey
License: UNKNOWN
Platform: UNKNOWN
Requires-Python: >=3.6
